<ArrayOfDATA_STRUCT><DATA_STRUCT><user_id>ANTON</user_id><email>anton@gmail.com</email><password>antonemail</password><nama>ANTON CANDRA</nama><alamat>JAKARTA</alamat><no_ktp>1234567890</no_ktp><no_telepon>02199890121</no_telepon><status>1</status></DATA_STRUCT><DATA_STRUCT><user_id>IBNU</user_id><email>ibnu@yahoo.com</email><password>ibnuemail</password><nama>IBNU SETIAWAN</nama><alamat>TANJUNG DUREN</alamat><no_ktp>9876543210</no_ktp><no_telepon>089991212134</no_telepon><status>1</status></DATA_STRUCT></ArrayOfDATA_STRUCT>